pan_sdk_python-1.0.0.dist-info/DESCRIPTION.rst
pan_sdk_python-1.0.0.dist-info/METADATA
pan_sdk_python-1.0.0.dist-info/RECORD
pan_sdk_python-1.0.0.dist-info/WHEEL
pan_sdk_python-1.0.0.dist-info/metadata.json
pan_sdk_python-1.0.0.dist-info/top_level.txt
panclient/__init__.py
panclient/setup.py
panclient/brocade/__init__.py
panclient/brocade/brocade_client.py
panclient/brocade/models.py
panclient/common/__init__.py
panclient/common/abstract_client.py
panclient/common/abstract_model.py
panclient/common/cookie/__init__.py
panclient/common/cookie/cookie.py
panclient/common/exception/__init__.py
panclient/common/exception/pan_sdk_exception.py
panclient/common/http/__init__.py
panclient/common/http/request.py
panclient/common/profile/__init__.py
panclient/common/profile/http_profile.py
panclient/dataset/__init__.py
panclient/dataset/dataset_client.py
panclient/dataset/models.py
panclient/importdata/__init__.py
panclient/importdata/import_client.py
panclient/importdata/models.py
panclient/login/__init__.py
panclient/login/login_client.py
panclient/login/models.py
panclient/schema/__init__.py
panclient/schema/models.py
panclient/schema/schema_client.py
panclient/settings/__init__.py
panclient/settings/models.py
panclient/settings/settings_client.py
panclient/user/__init__.py
panclient/user/models.py
panclient/user/user_client.py
panclient/workflow/__init__.py
panclient/workflow/models.py
panclient/workflow/workflow_client.py
panclient/workspace/__init__.py
panclient/workspace/models.py
panclient/workspace/workspace_client.py
