Metadata-Version: 2.0
Name: pan-sdk-python
Version: 1.0.0
Summary: Panorama SDK for Python
Home-page: https://gogs.analyticservice.net/AASRND/pan-python-sdk
Author: tim.wang
Author-email: 317302030@qq.com
License: UNKNOWN
Platform: any
Classifier: Programming Language :: Python :: 3.6
Classifier: Programming Language :: Python :: 3.7
